cli/lztools.py
lztools/DateTime.py
lztools/Images.py
lztools/Input.py
lztools/LazyVariable.py
lztools/ProDefered.py
lztools/TempPath.py
lztools/TimedOperation.py
lztools/click.py
lztools/dating.py
lztools/debugging.py
lztools/extensions.py
lztools/pathing.py
lztools.core-1.2.18.dist-info/LICENSE.txt
lztools.core-1.2.18.dist-info/METADATA
lztools.core-1.2.18.dist-info/RECORD
lztools.core-1.2.18.dist-info/WHEEL
lztools.core-1.2.18.dist-info/entry_points.txt
lztools.core-1.2.18.dist-info/top_level.txt
